pytest_tempdir/__init__.py
pytest_tempdir/hookspec.py
pytest_tempdir/plugin.py
pytest_tempdir/version.py
pytest_tempdir-2019.10.12.dist-info/LICENSE
pytest_tempdir-2019.10.12.dist-info/METADATA
pytest_tempdir-2019.10.12.dist-info/WHEEL
pytest_tempdir-2019.10.12.dist-info/entry_points.txt
pytest_tempdir-2019.10.12.dist-info/top_level.txt
pytest_tempdir-2019.10.12.dist-info/RECORD
