Metadata-Version: 2.1
Name: pytest-tempdir
Version: 2019.10.12
Summary: Predictable and repeatable tempdir support.
Home-page: https://github.com/saltstack/pytest-tempdir
Author: Pedro Algarvio
Author-email: pedro@algarvio.me
Maintainer: Pedro Algarvio
Maintainer-email: pedro@algarvio.me
License: Apache Software License 2.0
Platform: UNKNOWN
Classifier: Development Status :: 4 - Beta
Classifier: Intended Audience :: Developers
Classifier: Topic :: Software Development :: Testing
Classifier: Programming Language :: Python
Classifier: Programming Language :: Python :: 2
Classifier: Programming Language :: Python :: 2.7
Classifier: Programming Language :: Python :: 3
Classifier: Programming Language :: Python :: 3.3
Classifier: Programming Language :: Python :: 3.4
Classifier: Programming Language :: Python :: 3.5
Classifier: Programming Language :: Python :: Implementation :: CPython
Classifier: Programming Language :: Python :: Implementation :: PyPy
Classifier: Operating System :: OS Independent
Classifier: License :: OSI Approved :: Apache Software License
Requires-Dist: pytest (>=2.8.1)
